InfixToPostfix/__init__.py
InfixToPostfix/infix_to_postfix.py
InfixToPostfix/ui.py
InfixToPostfix/data/conf
InfixToPostfix/data/style.qss
InfixToPostfix-1.0.7.dist-info/LICENSE
InfixToPostfix-1.0.7.dist-info/METADATA
InfixToPostfix-1.0.7.dist-info/WHEEL
InfixToPostfix-1.0.7.dist-info/top_level.txt
InfixToPostfix-1.0.7.dist-info/RECORD
