Metadata-Version: 2.1
Name: InfixToPostfix
Version: 1.0.7
Summary: A python module converts infix expressions to postfix expressions and includes a visual interface.
Home-page: https://github.com/RoiexLee/InfixToPostfiX
Author: RoiexLee
Author-email: luoyixaun1029@gmail.com
Requires-Python: >=3.11.0
License-File: LICENSE
Requires-Dist: PyQt6 (~=6.5.1)
